gopersonal/__init__.py
gopersonal/api.py
gopersonal/client.py
gopersonal/exceptions.py
gopersonal_sdk-0.1.0.dist-info/METADATA
gopersonal_sdk-0.1.0.dist-info/WHEEL
gopersonal_sdk-0.1.0.dist-info/top_level.txt
gopersonal_sdk-0.1.0.dist-info/RECORD
