Metadata-Version: 2.1
Name: gopersonal-sdk
Version: 0.1.0
Summary: An asynchronous Python SDK for the GoPersonal API
Home-page: https://github.com/yourusername/gopersonal-sdk
Author: Your Name
Author-email: your.email@example.com
Classifier: Development Status :: 3 - Alpha
Classifier: Intended Audience :: Developers
Classifier: License :: OSI Approved :: MIT License
Classifier: Operating System :: OS Independent
Classifier: Programming Language :: Python :: 3
Classifier: Programming Language :: Python :: 3.7
Classifier: Programming Language :: Python :: 3.8
Classifier: Programming Language :: Python :: 3.9
Classifier: Programming Language :: Python :: 3.10
Classifier: Programming Language :: Python :: 3.11
Requires-Python: >=3.7
Requires-Dist: aiohttp>=3.7.4
Provides-Extra: dev
Requires-Dist: pytest>=6.2.5; extra == "dev"
Requires-Dist: pytest-asyncio>=0.15.1; extra == "dev"
